contribution_complexity/__init__.py
contribution_complexity/complexity_types.py
contribution_complexity/compute.py
contribution_complexity/default_models.py
contribution_complexity/metrics.py
contribution_complexity/train_model_bkp.py
contribution_complexity-0.1.1.dist-info/entry_points.txt
contribution_complexity-0.1.1.dist-info/WHEEL
contribution_complexity-0.1.1.dist-info/METADATA
contribution_complexity-0.1.1.dist-info/RECORD
