Metadata-Version: 2.1
Name: contribution-complexity
Version: 0.1.1
Summary:  Tool to compute the complexity of a Git contributions 
Home-page: https://github.com/HelgeCPH/contribution-complexity
Author: HelgeCPH
Author-email: ropf@itu.dk
Requires-Python: >=3.9,<4.0
Classifier: Development Status :: 4 - Beta
Classifier: Environment :: Console
Classifier: Intended Audience :: Developers
Classifier: Intended Audience :: Education
Classifier: Intended Audience :: Science/Research
Classifier: License :: OSI Approved :: GNU General Public License v3 (GPLv3)
Classifier: Programming Language :: Python :: 3
Classifier: Programming Language :: Python :: 3.9
Classifier: Topic :: Software Development
Classifier: Topic :: Utilities
Requires-Dist: PyDriller (>=1.15.5,<2.0.0)
Requires-Dist: docopt (>=0.6.2,<0.7.0)
Requires-Dist: toml (>=0.10.2,<0.11.0)
Project-URL: Documentation, https://github.com/HelgeCPH/contribution-complexity/blob/main/README.md
Project-URL: Repository, https://github.com/HelgeCPH/contribution-complexity
